run.py
nethang/__init__.py
nethang/config_manager.py
nethang/extensions.py
nethang/id_manager.py
nethang/proc_lock.py
nethang/routes.py
nethang/simu_path.py
nethang/traffic_monitor.py
nethang/version.py
nethang/static/images/favicon.png
nethang/static/images/icon-bright-trans.png
nethang/static/images/icon-bright.png
nethang/static/images/icon-dark-trans.png
nethang/static/images/icon-dark.png
nethang/static/images/logo-bright-trans.png
nethang/static/images/logo-bright.png
nethang/static/images/logo-dark-trans.png
nethang/static/images/logo-dark.png
nethang/templates/about.html
nethang/templates/base.html
nethang/templates/config.html
nethang/templates/index.html
nethang/templates/login.html
nethang-0.1.7.dist-info/licenses/LICENSE
nethang-0.1.7.dist-info/METADATA
nethang-0.1.7.dist-info/WHEEL
nethang-0.1.7.dist-info/entry_points.txt
nethang-0.1.7.dist-info/top_level.txt
nethang-0.1.7.dist-info/RECORD
