Metadata-Version: 2.4
Name: nethang
Version: 0.1.7
Summary: A web-based tool for simulating network quality
Author-email: Hang Yin <stephen.yin.h@gmail.com>
License: MIT
Project-URL: Homepage, https://stephenyin.github.io/NetHang/
Project-URL: Repository, https://github.com/stephenyin/NetHang.git
Classifier: Development Status :: 3 - Alpha
Classifier: Intended Audience :: Developers
Classifier: Programming Language :: Python :: 3
Classifier: Programming Language :: Python :: 3.8
Classifier: Programming Language :: Python :: 3.9
Classifier: Programming Language :: Python :: 3.10
Classifier: Programming Language :: Python :: 3.11
Classifier: Operating System :: POSIX :: Linux
Requires-Python: >=3.8
License-File: LICENSE
Requires-Dist: Flask>=2.0.0
Requires-Dist: flask-socketio>=5.0.0
Requires-Dist: python-dotenv>=0.10.0
Requires-Dist: Werkzeug>=3.0.0
Requires-Dist: pyyaml>=5.0.0
Requires-Dist: netifaces>=0.10.0
Requires-Dist: tomli>=2.0.0
Requires-Dist: requests>=2.0.0
Provides-Extra: dev
Requires-Dist: pytest>=7.0.0; extra == "dev"
Requires-Dist: pytest-cov>=4.0.0; extra == "dev"
Requires-Dist: mypy>=1.0.0; extra == "dev"
Requires-Dist: types-PyYAML>=6.0.0; extra == "dev"
Requires-Dist: black>=22.0.0; extra == "dev"
Requires-Dist: flake8>=4.0.0; extra == "dev"
Requires-Dist: isort>=5.0.0; extra == "dev"
Dynamic: license-file
